{"schemaVersion":2,"source":"SZU qxfacx detail API","sourceId":"5cf94b8c355b4a1bb583e9848f618389","major":"2024级金融科技主修培养方案（留学生）","grade":"2024","studyType":"主修","department":"微众银行金融科技学院","parsedAt":"2026-07-13T04:47:21.066Z","hoursLabel":"总学时","cats":["公共艺术教育","创新创业（选修）","其他扩展通识课程","创新创业（必修）","大类平台课","实践类课程","基本通识课（必修）","专业核心课","专业选修课"],"courses":[[4,"0202660001","政治经济学","",3,"54","1","秋"],[8,"0208630001","管理学原理","",2,"36","1","秋"],[7,"1501020003","程序设计基础","",5,"108","1","秋"],[4,"1900600001","高等数学A（1）","",5,"108","1","秋"],[4,"1902210001","线性代数","",2,"36","1","秋"],[5,"5601000005","军事技能","",2,"112","1","秋"],[3,"8001710002","创新领航讲座","",1,"18","1,2","春秋"],[0,"1208040001","音乐欣赏","",2,"36","1,2,3,4,5,6","春秋"],[0,"1229920001","中国传统音乐赏析","",2,"36","1,2,3,4,5,6","春秋"],[0,"6300090001","中国艺术鉴赏与美学分析","",2,"36","1,2,3,4,5,6","春秋"],[0,"6301000002","大学艺术核心素养十八讲","",2,"36","1,2,3,4,5,6","春秋"],[0,"9900470001","艺术设计鉴赏","",2,"36","1,2,3,4,5,6","春秋"],[0,"9900990001","艺术与生活","",2,"36","1,2,3,4,5,6","春秋"],[0,"9901760001","艺术的星空：艺术美学十二讲","",2,"36","1,2,3,4,5,6","春秋"],[5,"8001710003","思政与社会实践","",2,"36","1,2,3,4,5,6,7,8","春秋"],[4,"0202210001","微观经济学","",4,"72","2","春"],[7,"0208640001","财务会计","",3,"54","2","春"],[8,"1500480001","面向对象程序设计","",2.5,"54","2","春"],[4,"1900640001","高等数学A（2）","",5,"108","2","春"],[8,"2901000019","商法","",2,"36","2","春"],[5,"9901860007","大学生劳动教育","",1,"36","2,3,4,5,6","春秋"],[7,"0208720001","公司金融","",3,"54","3","秋"],[8,"0208940001","人力资源管理","",2,"36","3","秋"],[4,"1900410001","概率论与数理统计","",3,"54","3","秋"],[1,"2601000001","云计算行业与创新创业对接范式","",1,"18","3","秋"],[1,"2601000003","区块链行业与创新创业对接范式","",1,"18","3","秋"],[7,"2901000014","金融学","",2,"36","3","秋"],[4,"2901000017","宏观经济学","",4,"72","3","秋"],[7,"2901000024","数据结构与算法","",5,"90","3","秋"],[8,"3601000080","计算机网络","",2,"36","3","秋"],[8,"0208680001","市场营销","",3,"54","4","春"],[7,"0208690001","投资管理","",3,"54","4","春"],[8,"0208710001","财务报表分析","",2,"36","4","春"],[8,"1903420001","数学建模","",3,"72","4","春"],[3,"2601000005","面向未来的创新创业概论","",1,"18","4","春"],[4,"2901000012","金融科技导论","",2,"36","4","春"],[7,"2901000016","计量经济学","",3,"54","4","春"],[8,"29190005","行为金融","",3,"54","4","春"],[8,"3601000079","计算机操作系统","",2,"36","4","春"],[7,"3601000081","数据库原理","",3,"54","4","春"],[1,"8001710005","创新创业自主实践","",1,"36","4","春"],[8,"3601000072","环境、社会和公司治理","",2,"36","4,6","春"],[8,"1902040001","数值分析","",3,"54","5","秋"],[1,"2601000002","大数据行业与创新创业对接范式","",1,"18","5","秋"],[1,"2601000004","人工智能行业与创新创业对接范式","",1,"18","5","秋"],[7,"2901000018","金融计量分析","",3,"54","5","秋"],[8,"29190009","公司估值","",3,"54","5","秋"],[8,"29190010","战略管理","",2,"36","5","秋"],[7,"3601000074","人工智能与机器学习","",4,"90","5","秋"],[8,"3601000078","区块链与虚拟货币","",2,"36","5","秋"],[8,"0208660001","金融基建概论","",3,"54","6","春"],[8,"0208670001","金融科技的监管与法律政策","",2,"36","6","春"],[8,"0208740001","金融工程","",3,"54","6","春"],[7,"0208750001","金融风险管理","",3,"54","6","春"],[8,"2901000008","金融科技应用前沿","",2,"36","6","春"],[7,"2901000020","云计算与大数据分析","",2,"36","6","春"],[8,"2901000027","网络安全","",2.5,"54","6","春"],[8,"29190008","创新管理","",2,"36","6","春"],[5,"29190011","专业实习","",2,"36","6","春"],[8,"3601000008","数据可视化","",2,"36","6","春"],[8,"3601000060","固定收益证券","",2,"36","6","春"],[8,"3601000077","数据挖掘","",2,"36","6","春"],[8,"29190002","风险投资与金融创新","",2,"36","7","秋"],[5,"29190012","金融科技实践","",2,"72","7","秋"],[8,"3601000005","商务智能分析","",2,"36","7","秋"],[5,"0001000001","毕业论文（设计）","",8,"288","7,8","春秋"],[2,"1300860009","大学计算机","",3,"72","",""],[2,"2300250001","古代文学名著选读","",2,"36","",""],[2,"2300270001","古代汉语基础","",2,"36","",""],[6,"2300320001","中国概况","",2,"36","",""],[2,"2300380001","高级汉语综合（1）","",6,"108","",""],[2,"2300400001","中国现当代文学作品赏析（1）","",2,"36","",""],[2,"2300440001","高级汉语综合（2）","",6,"108","",""],[2,"2300460001","中国现当代文学作品赏析（2）","",2,"36","",""],[2,"2300470001","中国文化概论","",2,"36","",""],[6,"2300780001","中国法律与社会（国际班）","",2,"36","",""],[2,"2300950001","深圳概况","",2,"36","",""],[2,"2300990001","初级汉语综合（2）","",8,"144","",""],[2,"2301030001","中级汉语听说（1）","",6,"108","",""],[2,"2301050001","初级汉语听力（1）","",4,"72","",""],[2,"2301170001","中级汉语读写（2）","",4,"72","",""],[2,"2301190001","初级汉语口语（1）","",6,"108","",""],[2,"2301210001","中级汉语综合（1）","",8,"144","",""],[2,"2301280001","初级汉语口语（2）","",6,"108","",""],[2,"2301310001","初级汉语综合（1）","",8,"144","",""],[2,"2301320001","中级汉语读写（1）","",4,"72","",""],[2,"2301430001","初级汉语听力（2）","",4,"72","",""],[2,"5300040001","体育课（1）","",0.5,"36","",""],[2,"5300050001","体育课（2）","",0.5,"36","",""],[2,"5300060001","体育课（3）","",0.5,"36","",""],[2,"5300070001","体育课（4）","",0.5,"36","",""],[1,"8001710004","创新创业短课","",1,"18","",""],[0,"0501990308","弦乐室内乐团合奏","",2,"36","1,2,3,4,5,6","春秋"],[0,"0501990348","艺术与生命教育","",2,"36","1,2,3,4,5,6","春秋"],[0,"0701990268","中西方书写美学","",2,"36","1,2,3,4,5,6","春秋"],[0,"0501990358","艺术陶冶与审美体验","",2,"36","1,2,3,4,5,6","春秋"],[0,"0501990369","中国故事与戏剧美育","",2,"36","1,2,3,4,5,6","春秋"],[0,"0501990370","胶片摄影与古典印相","",2,"36","1,2,3,4,5,6","春秋"],[0,"0501990371","电影与女性","",2,"36","1,2,3,4,5,6","春秋"],[0,"0701990300","西语国家影视作品赏析","",2,"36","1,2,3,4,5,6","春秋"],[0,"1001990076","中国古代建筑艺术与技术赏析","",2,"36","1,2,3,4,5,6","春秋"],[0,"3501000021","艺术作品赏析","",2,"36","1,2,3,4,5,6","春秋"],[0,"3501000022","即兴编舞入门","",2,"36","1,2,3,4,5,6","春秋"],[0,"3501000023","音乐审美与创意实践","",2,"36","1,2,3,4,5,6","春秋"],[0,"3501000024","情绪表达手绘","",2,"54","1,2,3,4,5,6","春秋"],[0,"3501000025","版画赏析入门","",2,"36","1,2,3,4,5,6","春秋"]],"req":[{"mod":"通识模块","min":39,"subs":[{"name":"基本通识课（必修）","min":4,"cats":[6],"note":""},{"name":"扩展通识选修课","min":35,"cats":[0,2],"note":"包括公共选修课及非本专业开设的专业课程，涵盖人文艺术、社会科学、自然科学、生命科学、创新创业和中华文化六大类。学生须自主选修不少于6学分的扩展通识课，其中公共艺术教育课程选修不少于2学分，思想政治理论选择性必修课程不少于1门。"}]},{"mod":"专业模块","min":92,"subs":[{"name":"大类平台课","min":28,"cats":[4],"note":""},{"name":"专业核心课","min":39,"cats":[7],"note":""},{"name":"专业选修课","min":25,"cats":[8],"note":""}]},{"mod":"实践模块","min":17,"subs":[{"name":"实践类课程","min":17,"cats":[5],"note":""}]},{"mod":"创新创业模块","min":3,"subs":[{"name":"创新创业（选修）","min":1,"cats":[1],"note":""},{"name":"创新创业（必修）","min":2,"cats":[3],"note":""}]}],"totalMin":151,"rules":[{"type":"credit","cat":0,"min":2,"label":"公共艺术教育"}]}
